dawiq/__init__.py
dawiq/datawidget.py
dawiq/delegate.py
dawiq/fieldwidgets.py
dawiq/multitype.py
dawiq/py.typed
dawiq/qt_compat.py
dawiq/typing.py
dawiq/version.py
dawiq/tests/__init__.py
dawiq/tests/test_datawidget.py
dawiq/tests/test_delegate.py
dawiq/tests/test_fieldwidgets.py
dawiq/tests/test_multitype.py
dawiq/tests/test_qt_compat.py
dawiq-1.0.1.dist-info/LICENSE
dawiq-1.0.1.dist-info/METADATA
dawiq-1.0.1.dist-info/WHEEL
dawiq-1.0.1.dist-info/top_level.txt
dawiq-1.0.1.dist-info/RECORD
