Metadata-Version: 2.1
Name: dawiq
Version: 1.0.1
Summary: Package to construct Qt widgets from dataclasses
Home-page: https://github.com/JSS95/dawiq
Author: Jisoo Song
Author-email: jeesoo9595@snu.ac.kr
Maintainer: Jisoo Song
Maintainer-email: jeesoo9595@snu.ac.kr
License: MIT
Classifier: Development Status :: 5 - Production/Stable
Classifier: Intended Audience :: Developers
Classifier: License :: OSI Approved :: MIT License
Classifier: Operating System :: OS Independent
Classifier: Programming Language :: Python
Classifier: Programming Language :: Python :: 3
Classifier: Programming Language :: Python :: 3.9
Classifier: Programming Language :: Python :: 3.10
Classifier: Topic :: Software Development
Classifier: Topic :: Software Development :: Libraries :: Python Modules
Classifier: Topic :: Software Development :: User Interfaces
Classifier: Topic :: Software Development :: Widget Sets
Requires-Python: >=3.9
License-File: LICENSE
Provides-Extra: doc
Requires-Dist: numpydoc ; extra == 'doc'
Requires-Dist: sphinx (<5.2) ; extra == 'doc'
Requires-Dist: sphinx-code-tabs ; extra == 'doc'
Requires-Dist: sphinx-rtd-theme ; extra == 'doc'
Provides-Extra: full
Requires-Dist: pytest-qt ; extra == 'full'
Requires-Dist: sphinx-code-tabs ; extra == 'full'
Requires-Dist: cattrs ; extra == 'full'
Requires-Dist: sphinx-rtd-theme ; extra == 'full'
Requires-Dist: pytest-xvfb ; extra == 'full'
Requires-Dist: pytest ; extra == 'full'
Requires-Dist: mypy ; extra == 'full'
Requires-Dist: flake8 ; extra == 'full'
Requires-Dist: black ; extra == 'full'
Requires-Dist: sphinx (<5.2) ; extra == 'full'
Requires-Dist: numpydoc ; extra == 'full'
Provides-Extra: test
Requires-Dist: black ; extra == 'test'
Requires-Dist: cattrs ; extra == 'test'
Requires-Dist: flake8 ; extra == 'test'
Requires-Dist: mypy ; extra == 'test'
Requires-Dist: pytest ; extra == 'test'
Requires-Dist: pytest-qt ; extra == 'test'
Provides-Extra: test-ci
Requires-Dist: black ; extra == 'test-ci'
Requires-Dist: cattrs ; extra == 'test-ci'
Requires-Dist: flake8 ; extra == 'test-ci'
Requires-Dist: mypy ; extra == 'test-ci'
Requires-Dist: pytest ; extra == 'test-ci'
Requires-Dist: pytest-qt ; extra == 'test-ci'
Requires-Dist: pytest-xvfb ; extra == 'test-ci'
